csarxivcontextserver/__init__.py
csarxivcontextserver/server.py
csarxivcontextserver-0.1.0.dist-info/METADATA
csarxivcontextserver-0.1.0.dist-info/WHEEL
csarxivcontextserver-0.1.0.dist-info/entry_points.txt
csarxivcontextserver-0.1.0.dist-info/RECORD
