Metadata-Version: 2.4
Name: csarxivcontextserver
Version: 0.1.0
Summary: A MCP server project
Author-email: bai-z-l <b@iziliang.com>
Requires-Python: >=3.13
Requires-Dist: aiohttp>=3.9.0
Requires-Dist: beautifulsoup4>=4.12.0
Requires-Dist: lxml>=4.9.0
Requires-Dist: mcp>=1.9.1
Requires-Dist: requests>=2.31.0
